hadrosaur/__init__.py
hadrosaur/main.py
hadrosaur-0.4.1.dist-info/WHEEL
hadrosaur-0.4.1.dist-info/METADATA
hadrosaur-0.4.1.dist-info/RECORD
