Metadata-Version: 2.1
Name: hadrosaur
Version: 0.4.1
Summary: Manage statuses for a large amount of data analysis resources, such as files, imports, etc.
Home-page: https://github.com/jayrbolton/hadrosaur
License: MIT
Author: Jay R Bolton
Author-email: jayrbolton@gmail.com
Requires-Python: >=3.6
Classifier: License :: OSI Approved :: MIT License
Classifier: Programming Language :: Python :: 3
Classifier: Programming Language :: Python :: 3.6
Classifier: Programming Language :: Python :: 3.7
Classifier: Programming Language :: Python :: 3.8
Requires-Dist: plyvel (>=1.2.0)
Project-URL: Documentation, https://github.com/jayrbolton/hadrosaur
Project-URL: Repository, https://github.com/jayrbolton/hadrosaur
